yasfb/__init__.py
yasfb/formatter.py
yasfb-0.7.1.dist-info/DESCRIPTION.rst
yasfb-0.7.1.dist-info/METADATA
yasfb-0.7.1.dist-info/RECORD
yasfb-0.7.1.dist-info/WHEEL
yasfb-0.7.1.dist-info/metadata.json
yasfb-0.7.1.dist-info/pbr.json
yasfb-0.7.1.dist-info/top_level.txt
yasfb-0.7.1.dist-info/zip-safe
