Metadata-Version: 2.0
Name: yasfb
Version: 0.7.1
Summary: Yet Another Sphinx Feed Builder
Home-page: https://github.com/dhellmann/yasfb
Author: Doug Hellmann
Author-email: doug@doughellmann.com
License: BSD
Keywords: Sphinx
Platform: UNKNOWN
Classifier: Development Status :: 4 - Beta
Classifier: Environment :: Console
Classifier: Environment :: Web Environment
Classifier: Intended Audience :: Developers
Classifier: License :: OSI Approved :: BSD License
Classifier: Operating System :: OS Independent
Classifier: Programming Language :: Python
Classifier: Programming Language :: Python :: 2
Classifier: Programming Language :: Python :: 2.7
Classifier: Topic :: Documentation
Classifier: Topic :: Utilities
Requires-Dist: Sphinx (>=0.6)
Requires-Dist: pyquery
